sculpture/__init__.py
sculpture/sculpture.py
sculpture-0.1.1.dist-info/METADATA
sculpture-0.1.1.dist-info/WHEEL
sculpture-0.1.1.dist-info/top_level.txt
sculpture-0.1.1.dist-info/RECORD
