Metadata-Version: 2.1
Name: sculpture
Version: 0.1.1
Summary: A small model api template
Home-page: https://github.com/pypa/sampleproject
Author: Xian-Yun Tang
Author-email: xt1800i@gmail.com
Classifier: Programming Language :: Python :: 3
Classifier: License :: OSI Approved :: MIT License
Classifier: Operating System :: OS Independent
Requires-Dist: click (==8.1.3)
Requires-Dist: Flask (==2.2.3)
Requires-Dist: importlib-metadata (==6.0.0)
Requires-Dist: itsdangerous (==2.1.2)
Requires-Dist: Jinja2 (==3.1.2)
Requires-Dist: MarkupSafe (==2.1.2)
Requires-Dist: waitress (==2.1.2)
Requires-Dist: Werkzeug (==2.2.3)
Requires-Dist: zipp (==3.15.0)
